{
  "temperature": 0.8,
  "downfall": 0.4,
  "effects": {
    "sky_color": 15073060,
    "fog_color": 15073060,
    "water_color": 15073060,
    "water_fog_color": 15073060,
    "grass_color": 16776960,
    "foliage_color": 16768256,
    "particle": {
      "options": {
        "type": "falling_dust",
        "block_state": "minecraft:yellow_concrete"
      },
      "probability": 0.02
    }
  },
  "spawners": {},
  "spawn_costs": {},
  "carvers": {},
  "features": [],
  "has_precipitation": true
}
