{
  "inherit": [
    "civex:shafts",
    {
      "name": "civex:high_fuel_low_metal",
      "merge": {
        "structures": "top",
        "lore": "bottom"
      }
    }
  ],
  "lore": [
    {
      "text": "Difficulty: ☆☆☆☆",
      "color": "yellow"
    }
  ],
  "biome": "civex:acid",
  "base_block": "minecraft:dripstone_block",
  "dimension": "minecraft:the_nether",
  "start_y": 163,
  "air_block": [
    {
      "min": 0,
      "max": 150,
      "block": "water"
    },
    {
      "min": 151,
      "max": 255,
      "block": "air"
    }
  ],
  "structures": {
    "ustal": {
      "type": "descent_into_darkness:patch",
      "block": {
        "type": "minecraft:simple_state_provider",
        "state": {
          "Name": "minecraft:pointed_dripstone",
          "Properties": {
            "vertical_direction": "up",
            "thickness": "tip"
          }
        }
      },
      "edges": [
        "floor"
      ],
      "can_place_on": "minecraft:dripstone_block",
      "can_replace": "minecraft:air",
      "count": 0.25
    },
    "ustal2": {
      "type": "descent_into_darkness:patch",
      "block": {
        "type": "minecraft:simple_state_provider",
        "state": {
          "Name": "minecraft:pointed_dripstone",
          "Properties": {
            "vertical_direction": "up",
            "thickness": "tip_merge"
          }
        }
      },
      "edges": [
        "floor"
      ],
      "can_place_on": "minecraft:dripstone_block",
      "can_replace": "minecraft:air",
      "count": 0.25
    },
    "ustal3": {
      "type": "descent_into_darkness:patch",
      "block": {
        "type": "minecraft:simple_state_provider",
        "state": {
          "Name": "minecraft:pointed_dripstone",
          "Properties": {
            "vertical_direction": "down",
            "thickness": "tip_merge"
          }
        }
      },
      "edges": [
        "ceiling"
      ],
      "can_place_on": "minecraft:dripstone_block",
      "can_replace": "minecraft:air",
      "count": 0.25
    },
    "ustal4": {
      "type": "descent_into_darkness:patch",
      "block": {
        "type": "minecraft:simple_state_provider",
        "state": {
          "Name": "minecraft:pointed_dripstone",
          "Properties": {
            "vertical_direction": "down",
            "thickness": "tip"
          }
        }
      },
      "edges": [
        "ceiling"
      ],
      "can_place_on": "minecraft:dripstone_block",
      "can_replace": "minecraft:air",
      "count": 0.25
    }
  }
}